FeynmS/__init__.py
FeynmS/algorithms/__init__.py
FeynmS/algorithms/grover.py
FeynmS/algorithms/phase_estimation.py
FeynmS/algorithms/qft.py
FeynmS/algorithms/teleportation.py
FeynmS/core/__init__.py
FeynmS/core/circuit.py
FeynmS/core/gates.py
FeynmS/core/qubit.py
FeynmS/examples/__init__.py
FeynmS/examples/grover_example.py
FeynmS/examples/teleportation_example.py
FeynmS/tests/__init__.py
FeynmS/tests/test_circuit.py
FeynmS/tests/test_gates.py
FeynmS/tests/test_qubit.py
FeynmS/tests/integration/__init__.py
FeynmS/tests/integration/test_algorithms.py
FeynmS/utils/__init__.py
FeynmS/utils/state_utils.py
FeynmS/utils/validation.py
FeynmS/visualization/__init__.py
FeynmS/visualization/plotting.py
feynms-0.1.5.dist-info/METADATA
feynms-0.1.5.dist-info/WHEEL
feynms-0.1.5.dist-info/top_level.txt
feynms-0.1.5.dist-info/RECORD
