Metadata-Version: 2.4
Name: FeynmS
Version: 0.1.5
Summary: A Python library for quantum computing simulation.
Home-page: https://github.com/Miguell-J/FeynmS
Author: Miguel Araújo Julio
Author-email: Miguel Araújo Julio <Julioaraujo.guel@gmail.com>
License: MIT
Project-URL: Homepage, https://github.com/Miguell-J/FeynmS
Requires-Python: >=3.7
Requires-Dist: numpy>=1.19
Requires-Dist: scipy>=1.7
Requires-Dist: matplotlib>=3.4
Requires-Dist: qiskit>=0.34
Dynamic: author
Dynamic: home-page
Dynamic: requires-python
